[
  {
    "image": "https://i.ibb.co/vxsKMbG4/WhatsApp.png",
    "title": "WhatsApp",
    "companyName": "WhatsApp LLC",
    "id": 1,
    "description": "WhatsApp is a free, simple, and secure messaging and calling application that allows people from all over the world to communicate instantly. You can send text messages, voice messages, make video and voice calls, share images, documents, user locations, and other media securely with end-to-end encryption. It is widely used for personal, professional, and group communications.",
    "size": 95,
    "reviews": "185M",
    "ratingAvg": 4.3,
    "downloads": "960M",
    "ratings": [
      { "name": "1 star", "count": "2.4M" },
      { "name": "2 star", "count": "1.6M" },
      { "name": "3 star", "count": "5M" },
      { "name": "4 star", "count": "15M" },
      { "name": "5 star", "count": "162M" }
    ]
  },
  {
    "image": "https://i.ibb.co/ZRMMpfSQ/Facebook.png",
    "title": "Facebook",
    "companyName": "Meta Platforms, Inc.",
    "id": 2,
    "description": "Facebook helps you connect with friends, family, and communities around shared interests. You can post updates, share photos and videos, join groups, and participate in events. It is one of the most popular social networking platforms in the world, widely used for personal interactions, professional networking, and community engagement.",
    "size": 110,
    "reviews": "125M",
    "ratingAvg": 4.1,
    "downloads": "740M",
    "ratings": [
      { "name": "1 star", "count": "6M" },
      { "name": "2 star", "count": "5M" },
      { "name": "3 star", "count": "9M" },
      { "name": "4 star", "count": "22M" },
      { "name": "5 star", "count": "83M" }
    ]
  },
  {
    "image": "https://i.ibb.co/d47nydK4/Instagram.png",
    "title": "Instagram",
    "companyName": "Meta Platforms, Inc.",
    "id": 3,
    "description": "Instagram is a photo and video sharing social networking service that allows users to capture, edit, and share content with friends and followers. With features like Stories, Reels, IGTV, and Explore, it is widely used for personal expression, influencer marketing, and brand promotion. It also supports messaging and interactive features to engage with your audience.",
    "size": 150,
    "reviews": "147M",
    "ratingAvg": 4.4,
    "downloads": "842M",
    "ratings": [
      { "name": "1 star", "count": "4M" },
      { "name": "2 star", "count": "3.2M" },
      { "name": "3 star", "count": "9M" },
      { "name": "4 star", "count": "28M" },
      { "name": "5 star", "count": "102M" }
    ]
  },
  {
    "image": "https://i.ibb.co/3gHSWpF/X-Twitter.png",
    "title": "X (Twitter)",
    "companyName": "X Corp.",
    "id": 4,
    "description": "X, formerly Twitter, is a microblogging platform that allows users to post short messages called tweets, follow accounts, share updates, news, and interact globally. It supports media sharing, trending topics, hashtags, and direct messaging. It is widely used for news, discussions, and real-time conversations around the world.",
    "size": 89,
    "reviews": "89M",
    "ratingAvg": 4.0,
    "downloads": "100M",
    "ratings": [
      { "name": "1 star", "count": "4.1M" },
      { "name": "2 star", "count": "3.3M" },
      { "name": "3 star", "count": "7.1M" },
      { "name": "4 star", "count": "19M" },
      { "name": "5 star", "count": "55.5M" }
    ]
  },
  {
    "image": "https://i.ibb.co/SDkgk6zs/Youtube.png",
    "title": "YouTube",
    "companyName": "Google LLC",
    "id": 5,
    "description": "YouTube is a video-sharing platform where users can watch, upload, and share videos of all kinds, including music, tutorials, vlogs, movies, and live streams. Creators can monetize their content, interact with their audience through comments, and build communities. It is the largest video-sharing website in the world and widely used for entertainment, education, and marketing.",
    "size": 175,
    "reviews": "120M",
    "ratingAvg": 4.5,
    "downloads": "967M",
    "ratings": [
      { "name": "1 star", "count": "3.2M" },
      { "name": "2 star", "count": "2.8M" },
      { "name": "3 star", "count": "6.4M" },
      { "name": "4 star", "count": "20M" },
      { "name": "5 star", "count": "88M" }
    ]
  },
  {
    "image": "https://i.ibb.co/3yywhrks/TikTok.png",
    "title": "TikTok",
    "companyName": "ByteDance",
    "id": 6,
    "description": "TikTok is a platform for creating and sharing short-form videos that entertain, inspire, and connect people worldwide. Users can explore trends, music, and creative effects, while creators engage with audiences through challenges, collaborations, and livestreaming. It is widely used for entertainment, education, and brand promotion.",
    "size": 165,
    "reviews": "98M",
    "ratingAvg": 4.4,
    "downloads": "500M",
    "ratings": [
      { "name": "1 star", "count": "3.5M" },
      { "name": "2 star", "count": "2.8M" },
      { "name": "3 star", "count": "6.2M" },
      { "name": "4 star", "count": "21M" },
      { "name": "5 star", "count": "64.5M" }
    ]
  },
  {
    "image": "https://i.ibb.co/bRz82Qm7/Spotify.png",
    "title": "Spotify",
    "companyName": "Spotify AB",
    "id": 7,
    "description": "Spotify is a digital music service that gives you access to millions of songs, podcasts, and playlists for free. Users can create and share playlists, follow favorite artists, and discover new music with personalized recommendations. It is widely used for streaming music, podcasts, and audio content worldwide.",
    "size": 130,
    "reviews": "92M",
    "ratingAvg": 4.4,
    "downloads": "100M",
    "ratings": [
      { "name": "1 star", "count": "2.1M" },
      { "name": "2 star", "count": "1.6M" },
      { "name": "3 star", "count": "5.1M" },
      { "name": "4 star", "count": "18M" },
      { "name": "5 star", "count": "65M" }
    ]
  },
  {
    "image": "https://i.ibb.co/LDtdZw8W/Google-Map.png",
    "title": "Google Maps",
    "companyName": "Google LLC",
    "id": 8,
    "description": "Google Maps helps you navigate your world faster and easier with real-time GPS navigation, traffic conditions, route planning, and points of interest. You can explore nearby businesses, get directions for driving, walking, biking, or public transportation, and save favorite locations. It is widely used for travel, commuting, and exploration.",
    "size": 75,
    "reviews": "103M",
    "ratingAvg": 4.6,
    "downloads": "849M",
    "ratings": [
      { "name": "1 star", "count": "1.9M" },
      { "name": "2 star", "count": "1.1M" },
      { "name": "3 star", "count": "4M" },
      { "name": "4 star", "count": "18M" },
      { "name": "5 star", "count": "78M" }
    ]
  },
  {
    "image": "https://i.ibb.co/ZpdcT6tx/Gmail.png",
    "title": "Gmail",
    "companyName": "Google LLC",
    "id": 9,
    "description": "Gmail is a secure, smart, and easy-to-use email service from Google. It provides powerful spam protection, smart categorization, scheduling, search, and integration with other Google services. Users can send and receive emails instantly, manage multiple accounts, and organize their inbox efficiently.",
    "size": 85,
    "reviews": "64M",
    "ratingAvg": 4.5,
    "downloads": "990M",
    "ratings": [
      { "name": "1 star", "count": "1.6M" },
      { "name": "2 star", "count": "1.1M" },
      { "name": "3 star", "count": "3.2M" },
      { "name": "4 star", "count": "12M" },
      { "name": "5 star", "count": "46M" }
    ]
  },
  {
    "image": "https://i.ibb.co/Z6hQcGXh/Linkedin.png",
    "title": "LinkedIn",
    "companyName": "Microsoft Corporation",
    "id": 10,
    "description": "LinkedIn is the world's largest professional networking platform. It allows users to connect with colleagues, industry experts, and potential employers. Users can share professional updates, publish articles, search and apply for jobs, join groups, and build a professional online presence. It is widely used for career development, business networking, and industry insights.",
    "size": 102,
    "reviews": "42M",
    "ratingAvg": 4.3,
    "downloads": "200M",
    "ratings": [
      { "name": "1 star", "count": "1.5M" },
      { "name": "2 star", "count": "0.9M" },
      { "name": "3 star", "count": "2.2M" },
      { "name": "4 star", "count": "8M" },
      { "name": "5 star", "count": "29.5M" }
    ]
  },
  {
    "image": "https://i.ibb.co/QF3WnYj7/Netflix.png",
    "title": "Netflix",
    "companyName": "Netflix, Inc.",
    "id": 11,
    "description": "Netflix is a streaming service that offers a wide variety of award-winning TV shows, movies, anime, documentaries, and more on thousands of internet-connected devices. You can watch as much as you want, anytime, anywhere, without a single commercial. It also allows users to create profiles, track progress, and receive personalized recommendations based on viewing history.",
    "size": 160,
    "reviews": "112M",
    "ratingAvg": 4.5,
    "downloads": "100M",
    "ratings": [
      { "name": "1 star", "count": "3.2M" },
      { "name": "2 star", "count": "2.5M" },
      { "name": "3 star", "count": "5.8M" },
      { "name": "4 star", "count": "21M" },
      { "name": "5 star", "count": "80.5M" }
    ]
  },
  {
    "image": "https://i.ibb.co/Q3PyBdnr/Pinterest.png",
    "title": "Pinterest",
    "companyName": "Pinterest, Inc.",
    "id": 12,
    "description": "Pinterest is a visual discovery engine for finding ideas like recipes, home and style inspiration, and more. Users can explore Pins, create boards, save ideas, and share content with others. It is widely used for planning projects, discovering trends, and inspiration for personal or professional purposes.",
    "size": 85,
    "reviews": "52M",
    "ratingAvg": 4.6,
    "downloads": "100M",
    "ratings": [
      { "name": "1 star", "count": "1.2M" },
      { "name": "2 star", "count": "0.9M" },
      { "name": "3 star", "count": "2M" },
      { "name": "4 star", "count": "7M" },
      { "name": "5 star", "count": "41M" }
    ]
  },
  {
    "image": "https://i.ibb.co/gFFspQty/Zoom.png",
    "title": "Zoom",
    "companyName": "Zoom Video Communications",
    "id": 13,
    "description": "Zoom is a cloud-based video communications app that allows users to meet online, with or without video. Users can join webinars, online meetings, and conference rooms from any device. It also provides screen sharing, recording, virtual backgrounds, and collaboration tools, making it widely used for remote work, education, and social gatherings.",
    "size": 115,
    "reviews": "77M",
    "ratingAvg": 4.3,
    "downloads": "100M",
    "ratings": [
      { "name": "1 star", "count": "2.2M" },
      { "name": "2 star", "count": "1.7M" },
      { "name": "3 star", "count": "3.8M" },
      { "name": "4 star", "count": "11M" },
      { "name": "5 star", "count": "58M" }
    ]
  },
  {
    "image": "https://i.ibb.co/gZgh0LBV/Uber.png",
    "title": "Uber",
    "companyName": "Uber Technologies, Inc.",
    "id": 14,
    "description": "Uber is a ride-hailing service that connects passengers with drivers through a mobile app. Users can request rides, track drivers in real-time, pay digitally, and rate their trip experience. It also offers food delivery, freight services, and advanced mobility solutions. Uber is widely used for convenient transportation in cities worldwide.",
    "size": 97,
    "reviews": "67M",
    "ratingAvg": 4.4,
    "downloads": "100M",
    "ratings": [
      { "name": "1 star", "count": "1.7M" },
      { "name": "2 star", "count": "1.2M" },
      { "name": "3 star", "count": "3M" },
      { "name": "4 star", "count": "9.5M" },
      { "name": "5 star", "count": "51.6M" }
    ]
  },
  {
    "image": "https://i.ibb.co/GSg6D2H/Amazon.png",
    "title": "Amazon",
    "companyName": "Amazon Mobile LLC",
    "id": 15,
    "description": "Amazon is a global e-commerce platform that allows users to shop millions of products, read reviews, compare prices, and get fast delivery through Amazon Prime. The app also includes features like order tracking, wish lists, voice shopping with Alexa, and personalized recommendations. It is widely used for convenient online shopping and marketplace services.",
    "size": 140,
    "reviews": "123M",
    "ratingAvg": 4.5,
    "downloads": "59M",
    "ratings": [
      { "name": "1 star", "count": "3.5M" },
      { "name": "2 star", "count": "2.3M" },
      { "name": "3 star", "count": "5M" },
      { "name": "4 star", "count": "19M" },
      { "name": "5 star", "count": "94M" }
    ]
  },
  {
    "image": "https://i.ibb.co/N2WWXzNt/Google-Drive.png",
    "title": "Google Drive",
    "companyName": "Google LLC",
    "id": 16,
    "description": "Google Drive is a cloud storage service that allows users to save files securely and access them from any device. It supports document editing, sharing, collaboration, backup, and syncing across devices. Users can also organize files into folders, control sharing permissions, and integrate with Google Docs, Sheets, and Slides for productivity.",
    "size": 105,
    "reviews": "52M",
    "ratingAvg": 4.6,
    "downloads": "80M",
    "ratings": [
      { "name": "1 star", "count": "1.3M" },
      { "name": "2 star", "count": "1M" },
      { "name": "3 star", "count": "2.5M" },
      { "name": "4 star", "count": "8M" },
      { "name": "5 star", "count": "39.2M" }
    ]
  },
  {
    "image": "https://i.ibb.co/DPCLFcvv/Snapchat.png",
    "title": "Snapchat",
    "companyName": "Snap Inc.",
    "id": 17,
    "description": "Snapchat is a multimedia messaging app where users can send photos, videos, and messages that disappear after being viewed. It also includes Stories, Discover content, AR filters, and Snap Map for sharing location. It is widely used for private messaging, entertainment, and creative expression among young audiences.",
    "size": 88,
    "reviews": "95M",
    "ratingAvg": 4.3,
    "downloads": "96M",
    "ratings": [
      { "name": "1 star", "count": "3.1M" },
      { "name": "2 star", "count": "2.4M" },
      { "name": "3 star", "count": "5.2M" },
      { "name": "4 star", "count": "13M" },
      { "name": "5 star", "count": "71.3M" }
    ]
  },
  {
    "image": "https://i.ibb.co/sdnj8Chs/Trello.png",
    "title": "Trello",
    "companyName": "Atlassian",
    "id": 18,
    "description": "Trello is a project management app that helps teams organize tasks, projects, and workflows with boards, lists, and cards. Users can assign tasks, set due dates, add attachments, and collaborate in real-time. It is widely used for agile management, personal organization, and team collaboration in both professional and educational contexts.",
    "size": 65,
    "reviews": "12M",
    "ratingAvg": 4.5,
    "downloads": "10M",
    "ratings": [
      { "name": "1 star", "count": "0.21M" },
      { "name": "2 star", "count": "0.13M" },
      { "name": "3 star", "count": "0.4M" },
      { "name": "4 star", "count": "1.6M" },
      { "name": "5 star", "count": "9.6M" }
    ]
  },
  {
    "image": "https://i.ibb.co/bggRcJDz/Canva.png",
    "title": "Canva",
    "companyName": "Canva Pty Ltd",
    "id": 19,
    "description": "Canva is a graphic design platform that allows users to create presentations, social media graphics, posters, documents, and other visual content. It provides templates, drag-and-drop editing, stock photos, fonts, and collaboration tools. It is widely used by individuals, marketers, educators, and businesses for creating professional-looking designs easily.",
    "size": 125,
    "reviews": "67M",
    "ratingAvg": 4.8,
    "downloads": "50M",
    "ratings": [
      { "name": "1 star", "count": "0.9M" },
      { "name": "2 star", "count": "0.7M" },
      { "name": "3 star", "count": "2M" },
      { "name": "4 star", "count": "10M" },
      { "name": "5 star", "count": "53.4M" }
    ]
  },
  {
    "image": "https://i.ibb.co/XfcDDN81/Google-Play-Store.png",
    "title": "Google Play Store",
    "companyName": "Google LLC",
    "id": 20,
    "description": "Google Play Store is the official app store for Android devices. It allows users to discover, download, and update millions of apps, games, movies, and books. Users can leave reviews, rate apps, and receive personalized recommendations. It also provides developers with a platform to distribute and monetize their applications to a global audience.",
    "size": 145,
    "reviews": "184M",
    "ratingAvg": 4.5,
    "downloads": "100M",
    "ratings": [
      { "name": "1 star", "count": "4.2M" },
      { "name": "2 star", "count": "2.8M" },
      { "name": "3 star", "count": "7.2M" },
      { "name": "4 star", "count": "19M" },
      { "name": "5 star", "count": "151M" }
    ]
  }
]
